./.coveragerc
./.gitignore
./LICENSE
./MANIFEST.in
./README.md
./README.zh-CN.md
./config.jsonc.default
./config_manager.py
./config_utils.py
./enhanced_logging.py
./file_validator.py
./notification_manager.py
./notification_providers.py
./package-lock.json
./package.json
./pyproject.toml
./pytest.ini
./server.py
./shared_types.py
./task_queue.py
./test.py
./test_mcp_client.py
./uv.lock
./web_ui.py
./.github/dependabot.yml
./.github/assets/desktop_dark_content.png
./.github/assets/desktop_dark_no_content.png
./.github/assets/desktop_light_content.png
./.github/assets/desktop_light_no_content.png
./.github/assets/desktop_screenshot.png
./.github/assets/mobile_dark_content.png
./.github/assets/mobile_dark_no_content.png
./.github/assets/mobile_light_content.png
./.github/assets/mobile_light_no_content.png
./.github/assets/mobile_screenshot.png
./.github/workflows/release.yml
./.github/workflows/test.yml
./.github/workflows/vscode.yml
./.specify/memory/constitution.md
./.specify/scripts/bash/check-prerequisites.sh
./.specify/scripts/bash/common.sh
./.specify/scripts/bash/create-new-feature.sh
./.specify/scripts/bash/setup-plan.sh
./.specify/scripts/bash/update-agent-context.sh
./.specify/templates/agent-file-template.md
./.specify/templates/checklist-template.md
./.specify/templates/plan-template.md
./.specify/templates/spec-template.md
./.specify/templates/tasks-template.md
./docs/configuration.md
./docs/configuration.zh-CN.md
./docs/api/config_manager.md
./docs/api/config_utils.md
./docs/api/enhanced_logging.md
./docs/api/file_validator.md
./docs/api/index.md
./docs/api/notification_manager.md
./docs/api/notification_providers.md
./docs/api/task_queue.md
./docs/api.zh-CN/config_manager.md
./docs/api.zh-CN/config_utils.md
./docs/api.zh-CN/enhanced_logging.md
./docs/api.zh-CN/file_validator.md
./docs/api.zh-CN/index.md
./docs/api.zh-CN/notification_manager.md
./docs/api.zh-CN/notification_providers.md
./docs/api.zh-CN/task_queue.md
./icons/icon.svg
ai_intervention_agent-1.4.12.dist-info/METADATA
ai_intervention_agent-1.4.12.dist-info/WHEEL
ai_intervention_agent-1.4.12.dist-info/entry_points.txt
ai_intervention_agent-1.4.12.dist-info/licenses/LICENSE
ai_intervention_agent-1.4.12.dist-info/RECORD
