Metadata-Version: 2.4
Name: ai-intervention-agent
Version: 1.4.12
Summary: AI Intervention Agent: MCP server enabling real-time user intervention in AI-assisted development workflows.
Project-URL: Homepage, https://github.com/xiadengma/ai-intervention-agent
Project-URL: Repository, https://github.com/xiadengma/ai-intervention-agent
Project-URL: Issues, https://github.com/xiadengma/ai-intervention-agent/issues
Project-URL: Documentation, https://github.com/xiadengma/ai-intervention-agent#readme
Author-email: xiadengma <52972447+XIADENGMA@users.noreply.github.com>
License-Expression: MIT
License-File: LICENSE
Keywords: agent,ai,claude,cursor,feedback,intervention,mcp
Classifier: Development Status :: 4 - Beta
Classifier: Intended Audience :: Developers
Classifier: License :: OSI Approved :: MIT License
Classifier: Operating System :: OS Independent
Classifier: Programming Language :: Python :: 3
Classifier: Programming Language :: Python :: 3.11
Classifier: Programming Language :: Python :: 3.12
Classifier: Topic :: Scientific/Engineering :: Artificial Intelligence
Classifier: Topic :: Software Development :: Libraries :: Python Modules
Requires-Python: >=3.11
Requires-Dist: fastmcp>=2.10.5
Requires-Dist: flask-compress>=1.15.0
Requires-Dist: flask-cors>=5.0.0
Requires-Dist: flask-limiter>=3.12.0
Requires-Dist: flask>=3.1.0
Requires-Dist: markdown>=3.8.0
Requires-Dist: platformdirs>=4.3.0
Requires-Dist: plyer>=2.1.0
Requires-Dist: psutil>=6.1.0
Requires-Dist: pygments>=2.18.0
Requires-Dist: requests>=2.32.0
Requires-Dist: urllib3>=2.3.0
Requires-Dist: watchdog>=6.0.0
Requires-Dist: zeroconf>=0.146.0
Provides-Extra: dev
Requires-Dist: black>=23.0.0; extra == 'dev'
Requires-Dist: flake8>=7.2.0; extra == 'dev'
Requires-Dist: isort>=5.12.0; extra == 'dev'
Requires-Dist: mypy>=1.0.0; extra == 'dev'
Requires-Dist: pytest-cov>=6.2.1; extra == 'dev'
Requires-Dist: pytest-timeout>=2.3.0; extra == 'dev'
Requires-Dist: pytest>=8.4.0; extra == 'dev'
Requires-Dist: rcssmin>=1.1.2; extra == 'dev'
Requires-Dist: rjsmin>=1.2.5; extra == 'dev'
Requires-Dist: ruff>=0.8.0; extra == 'dev'
Requires-Dist: ty; extra == 'dev'
